{
    "destination_addresses" : [ "Ringtee 75, 50501 Tartu, Estonia" ],
    "origin_addresses" : [ "Juhan Liivi 2, 50409 Tartu, Estonia" ],
    "rows" : [
       {
          "elements" : [
             {
                "distance" : {
                   "text" : "4.2 km",
                   "value" : 4159
                },
                "duration" : {
                   "text" : "9 mins",
                   "value" : 560
                },
                "status" : "OK"
             }
          ]
       }
    ],
    "status" : "OK"
 }